opensesame_plugins/example/__init__.py
opensesame_plugins/example/example_plugin/__init__.py
opensesame_plugins/example/example_plugin/example_plugin.md
opensesame_plugins/example/example_plugin/example_plugin.png
opensesame_plugins/example/example_plugin/example_plugin.py
opensesame_plugins/example/example_plugin/example_plugin_large.png
opensesame_plugin_example-0.0.1.dist-info/METADATA
opensesame_plugin_example-0.0.1.dist-info/WHEEL
opensesame_plugin_example-0.0.1.dist-info/RECORD
